LICENSE
MANIFEST.in
README.md
setup.cfg
setup.py
python/byte_flux.egg-info/PKG-INFO
python/byte_flux.egg-info/SOURCES.txt
python/byte_flux.egg-info/dependency_links.txt
python/byte_flux.egg-info/requires.txt
python/byte_flux.egg-info/top_level.txt
python/flux/__init__.py
python/flux/ag_kernel_crossnode.py
python/flux/cpp_mod.py
python/flux/cpp_mod.pyi
python/flux/dist_utils.py
python/flux/gemm_rs_sm80.py
python/flux/util.py
python/flux/include/flux/flux.h
python/flux/include/flux/gemm_hparams.h
python/flux/include/flux/gemm_meta.h
python/flux/include/flux/gemm_operator_base.h
python/flux/include/flux/op_registry.h
python/flux/include/flux/op_registry_proto_utils.h
python/flux/include/flux/runtime_config.h
python/flux/include/flux/utils.h
python/flux/include/flux/ag_gemm/ths_op/all_gather_gemm_op.h
python/flux/include/flux/ag_gemm/ths_op/all_gather_gemm_op_crossnode.h
python/flux/include/flux/ag_gemm/ths_op/gemm_with_barrier.h
python/flux/include/flux/coll/ths_op/all_gather_op.h
python/flux/include/flux/coll/ths_op/all_gather_types.h
python/flux/include/flux/coll/ths_op/reduce_scatter_op.h
python/flux/include/flux/comm_none/ths_op/blockscale_gemm.h
python/flux/include/flux/comm_none/ths_op/gemm_grouped_v2.h
python/flux/include/flux/comm_none/ths_op/gemm_grouped_v3.h
python/flux/include/flux/comm_none/ths_op/gemm_only.h
python/flux/include/flux/gemm_rs/ths_op/gemm_reduce_scatter.h
python/flux/include/flux/gemm_rs/ths_op/helper_ops.h
python/flux/include/flux/moe_ag_scatter/ths_op/gemm_grouped_v2_ag_scatter.h
python/flux/include/flux/moe_ag_scatter/ths_op/gemm_grouped_v3_ag_scatter.h
python/flux/include/flux/moe_gather_rs/ths_op/gemm_grouped_v2_gather_rs.h
python/flux/include/flux/moe_gather_rs/ths_op/gemm_grouped_v3_gather_rs.h
python/flux/include/flux/moe_gather_rs/ths_op/moe_utils.h
python/flux/include/flux/moe_gather_rs/ths_op/topk_reduce_gather_rs.h
python/flux/include/flux/ths_op/flux_shm.h
python/flux/include/flux/ths_op/ths_op.h
python/flux/include/flux/ths_op/ths_pybind.h
python/flux/include/flux/ths_op/topo_utils.h
python/flux/include/flux/ths_op/util.h
python/flux/share/cmake/Flux/FluxConfig.cmake
python/flux/testing/__init__.py
